<?xml version="1.0" encoding="UTF-8"?>
<objects serializationModel="Studio.02.00.00">
	<object class="AudioFile" id="{a7c621b0-7ae7-4826-931b-3fe0964453be}">
		<property name="assetPath">
			<value>phone_pickup.mp3</value>
		</property>
		<property name="frequencyInKHz">
			<value>48</value>
		</property>
		<property name="channelCount">
			<value>2</value>
		</property>
		<property name="length">
			<value>0.55200000000000005</value>
		</property>
		<relationship name="masterAssetFolder">
			<destination>{ef961123-d105-420c-94ba-3978cc61b05b}</destination>
		</relationship>
	</object>
</objects>
